[
  {
    "slug": "privacy-policy",
    "titleKey": "Privacy Policy",
    "lastUpdatedKey": "2026-06-18",
    "bodyKey": ""
  },
  {
    "slug": "terms-of-use",
    "titleKey": "Terms of Use",
    "lastUpdatedKey": "2026-06-18",
    "bodyKey": ""
  },
  {
    "slug": "fair-practices-code",
    "titleKey": "Fair Practices Code",
    "lastUpdatedKey": "2026-06-18",
    "bodyKey": ""
  },
  {
    "slug": "cookie-policy",
    "titleKey": "Cookie Policy",
    "lastUpdatedKey": "2026-06-18",
    "bodyKey": ""
  },
  {
    "slug": "grievance-redressal",
    "titleKey": "Grievance Redressal",
    "lastUpdatedKey": "2026-06-18",
    "bodyKey": ""
  },
  {
    "slug": "rbi-dlg-disclosure",
    "titleKey": "RBI-DLG Disclosure",
    "lastUpdatedKey": "2026-06-18",
    "bodyKey": ""
  },
  {
    "slug": "consent-policy",
    "titleKey": "Consent Policy",
    "lastUpdatedKey": "2026-06-18",
    "bodyKey": ""
  }
]
